{
  "about_us": "关于我们",
  "practice_area": "实践领域",
  "industries": "行业",
  "news_insight": "新闻与见解",
  "publications": "出版物",
  "careers": "職業生涯",
  "international_calculators": "国际计算器",
  "contact_us": "联系我们",
  "search": "搜索",
  "ICC_Fee_Calculator": "国际刑事法庭费用计算器",
  "innovation_hub": "創新中心",

  "Arb_Fee_Calculator": "仲裁費計算器",
  "Beta_Phased_Message": "成本計算器處於測試階段",
  "our_team": "我們的隊伍",

  "user_sign_in": "登入",
  "sign_Up": "報名",
  "login": "登入",
  "register": "登記",
  "Legal_tech": "法律科技",
  "Generative_AI": "生成式人工智慧",
  "comparison_analysis": "比較分析",
  "Cost_Calculator": "成本計算器",

  "practice_area_Message1": "我們充滿活力的團隊提供經驗豐富的諮詢",
  "practice_area_Message2": "在不同的實踐領域",
  "art_law": "藝術法",
  "Bankruptcy_Restructuring_and_insolvency": "破產重整與破產",
  "Corporate_Advisory": "企業諮詢    ",
  "Domestic_Arbitration_and_Mediation": "國內仲裁與調解",
  "Fraud_asset_tracing_and_enforcement": "詐欺,資產追蹤與執法",
  "Intellectual_Property": "智慧財產",
  "International_Dispute_Resolution": "國際爭議解決",
  "Low_Bono": "低博諾",
  "Private_Client_Practice": "私人客戶實踐",
  "Real_Estate": "房地產",
  "Risk_Management_and_Compliance": "風險管理與合規",
  "Trial_and_Litigation": "審判及訴訟",

  "Subscribe_Newsletter": "訂閱時事通訊",
  "All_Rights_Reserved1": "© 2024 阿爾納法。版權所有",
  "All_Rights_Reserved2": "由 清晰的設計 設計",
  "Privacy_Policy": "隱私權政策",
  "Terms_Conditions": "條款及條件",
  "Disclaimer": "免責聲明",
  "insights": "見解",
  "arnaNews": "阿爾納新聞",
  "publication": "出版品",
  "podcast": "播客",
  "Log_in": "登入",
  "Translate": "翻譯"

}
